{"total_records":99,"records_with_species_name":57,"bins":{"count":46,"drill_down":{"entity":[{"name":null,"records":null},{"name":null,"records":null}]}},"countries":{"count":1,"drill_down":{"entity":[{"name":null,"records":null},{"name":null,"records":null}]}},"depositories":{"count":12,"drill_down":{"entity":[{"name":null,"records":null},{"name":null,"records":null}]}},"order":{"count":14,"drill_down":{"entity":[{"name":null,"records":null},{"name":null,"records":null}]}},"family":{"count":17,"drill_down":{"entity":[{"name":null,"records":null},{"name":null,"records":null}]}},"genus":{"count":21,"drill_down":{"entity":[{"name":null,"records":null},{"name":null,"records":null}]}},"species":{"count":23,"drill_down":{"entity":[{"name":null,"records":null},{"name":null,"records":null}]}}}